pyinnovativetrend/__init__.py
pyinnovativetrend/pyinnovativetrend.py
pyinnovativetrend/util.py
pyinnovativetrend/visualization.py
pyinnovativetrend-1.0.dist-info/LICENSE.txt
pyinnovativetrend-1.0.dist-info/METADATA
pyinnovativetrend-1.0.dist-info/WHEEL
pyinnovativetrend-1.0.dist-info/top_level.txt
pyinnovativetrend-1.0.dist-info/RECORD
