Metadata-Version: 2.1
Name: pyinnovativetrend
Version: 1.0
Summary: An innovative trend analysis and visualization tool
Author: Md Mehedi Hasan Prodhan
Author-email: mehediprodhan1613@outlook.com
Keywords: time series analysis,trend analysis,innovative trend,trend,ITA,ita
Requires-Python: >=3.7, <4
License-File: LICENSE.txt
Requires-Dist: numpy
Requires-Dist: pandas
Requires-Dist: matplotlib
Requires-Dist: scipy
